jmpcba_pulumi_common/__init__.py
jmpcba_pulumi_common/autoscaling/asg.py
jmpcba_pulumi_common-0.1.1.dist-info/METADATA
jmpcba_pulumi_common-0.1.1.dist-info/WHEEL
jmpcba_pulumi_common-0.1.1.dist-info/RECORD
