Metadata-Version: 2.1
Name: jmpcba_pulumi_common
Version: 0.1.1
Summary: 
Author: manu-caylent
Author-email: manuel.palacios@caylent.com
Requires-Python: >=3.10,<4.0
Classifier: Programming Language :: Python :: 3
Classifier: Programming Language :: Python :: 3.10
Classifier: Programming Language :: Python :: 3.11
Requires-Dist: pulumi (>=3.89.0,<4.0.0)
Requires-Dist: pulumi-aws (>=6.6.0,<7.0.0)
